<?xml version="1.0" encoding="utf-8" ?><dwsync><file name="slick.woff" server="allms-room.lsv.jp" local="3589897769" remote="3716772900" Dst="-1" /><file name="slick.ttf" server="allms-room.lsv.jp" local="3589897769" remote="3716772900" Dst="-1" /><file name="slick.svg" server="allms-room.lsv.jp" local="3589897769" remote="3716772900" Dst="-1" /><file name="slick.eot" server="allms-room.lsv.jp" local="3589897769" remote="3716772900" Dst="-1" /><file name="slick.woff" server="allms-room.lsv.jp//pub/" local="3589897769" remote="3716797380" Dst="-1" /><file name="slick.ttf" server="allms-room.lsv.jp//pub/" local="3589897769" remote="3716797380" Dst="-1" /><file name="slick.svg" server="allms-room.lsv.jp//pub/" local="3589897769" remote="3716797380" Dst="-1" /><file name="slick.eot" server="allms-room.lsv.jp//pub/" local="3589897769" remote="3716797380" Dst="-1" /><file name="slick.svg" server="allms-room.lsv.jp//pub/allms-room.com/" local="3589897769" remote="3717025680" Dst="-1" /><file name="slick.woff" server="allms-room.lsv.jp//pub/allms-room.com/" local="3589897769" remote="3717025680" Dst="-1" /><file name="slick.ttf" server="allms-room.lsv.jp//pub/allms-room.com/" local="3589897769" remote="3717025680" Dst="-1" /><file name="slick.eot" server="allms-room.lsv.jp//pub/allms-room.com/" local="3589897769" remote="3717025680" Dst="-1" /></dwsync>